tinui/ChangeLog.txt
tinui/LOGO.ico
tinui/Segoe Fluent Icons.ttf
tinui/TinUI.py
tinui/TinUIDialog.py
tinui/__init__.py
tinui/extension.py
tinui/gpl-3.0.md
tinui/lgpl-3.md
tinui/test/LOGO.png
tinui/test/breadcrumb.py
tinui/test/button.py
tinui/test/checkbutton.py
tinui/test/combobox.py
tinui/test/entry.py
tinui/test/extension.buttonlize.py
tinui/test/image.py
tinui/test/link.py
tinui/test/listbox.py
tinui/test/listview.py
tinui/test/maintest.py
tinui/test/navigation.py
tinui/test/onoff.py
tinui/test/pivot.py
tinui/test/progressbar.py
tinui/test/radiobox.py
tinui/test/radiobutton.py
tinui/test/ratingbar.py
tinui/test/scalebar.py
tinui/test/segmentbutton.py
tinui/test/table.py
tinui/test/test.py
tinui/test/treeview.py
tinui/test/tuxml.py
tinui/test/tuxmltest.py
tinui/test/ui.py
tinui/test/window.py
tinui/test/testpage/TinUIXml.xml
tinui/test/testpage/back.xml
tinui/test/testpage/barbutton.xml
tinui/test/testpage/breadcrumb.xml
tinui/test/testpage/button.xml
tinui/test/testpage/button2.xml
tinui/test/testpage/canvas.xml
tinui/test/testpage/checkbutton.xml
tinui/test/testpage/combobox.xml
tinui/test/testpage/entry.xml
tinui/test/testpage/expander.xml
tinui/test/testpage/flyout.xml
tinui/test/testpage/image.xml
tinui/test/testpage/info.xml
tinui/test/testpage/label.xml
tinui/test/testpage/labelframe.xml
tinui/test/testpage/link.xml
tinui/test/testpage/listbox.xml
tinui/test/testpage/listview.xml
tinui/test/testpage/menubar.xml
tinui/test/testpage/menubutton.xml
tinui/test/testpage/navigation.xml
tinui/test/testpage/notebook.xml
tinui/test/testpage/notecard.xml
tinui/test/testpage/onoff.xml
tinui/test/testpage/paragraph.xml
tinui/test/testpage/passwordbox.xml
tinui/test/testpage/picker.xml
tinui/test/testpage/pipspager.xml
tinui/test/testpage/pivot.xml
tinui/test/testpage/progressbar.xml
tinui/test/testpage/radiobox.xml
tinui/test/testpage/radiobutton.xml
tinui/test/testpage/ratingbar.xml
tinui/test/testpage/scalebar.xml
tinui/test/testpage/scrollbar.xml
tinui-6.11.1.dist-info/licenses/LICENSE.txt
tinui-6.11.1.dist-info/METADATA
tinui-6.11.1.dist-info/WHEEL
tinui-6.11.1.dist-info/top_level.txt
tinui-6.11.1.dist-info/RECORD
