Metadata-Version: 2.4
Name: tinui
Version: 6.11.1
Summary: 使用tkinter.Canvas绘制现代UI组件
Home-page: https://github.com/Smart-Space/TinUI
Author: Smart-Space
Author-email: smart-space@qq.com
License: GPL License
Classifier: Intended Audience :: Developers
Classifier: Natural Language :: Chinese (Simplified)
Classifier: Programming Language :: Python
Classifier: Topic :: Software Development :: Libraries
Requires-Python: >=3.6
License-File: LICENSE.txt
Dynamic: author
Dynamic: author-email
Dynamic: classifier
Dynamic: description
Dynamic: description-content-type
Dynamic: home-page
Dynamic: license
Dynamic: license-file
Dynamic: requires-python
Dynamic: summary
